__init__.py
mylove/__init__.py
mylove/mfunc.py
huangyinglan-0.1.3.dist-info/LICENSE
huangyinglan-0.1.3.dist-info/METADATA
huangyinglan-0.1.3.dist-info/WHEEL
huangyinglan-0.1.3.dist-info/entry_points.txt
huangyinglan-0.1.3.dist-info/top_level.txt
huangyinglan-0.1.3.dist-info/RECORD
