Metadata-Version: 2.2
Name: huangyinglan
Version: 0.1.3
Home-page: https://github.com/rinkeigun/svg
Author: Keigun Rin
Author-email: 
License: ライセンス
Classifier: Programming Language :: Python :: 3
Classifier: License :: OSI Approved :: MIT License
Classifier: Operating System :: OS Independent
Requires-Python: >=3.6
License-File: LICENSE
Requires-Dist: pytest
Requires-Dist: setuptools
Requires-Dist: wheel
Requires-Dist: twine
Dynamic: author
Dynamic: classifier
Dynamic: description
Dynamic: description-content-type
Dynamic: home-page
Dynamic: license
Dynamic: requires-dist
Dynamic: requires-python
